multidocs/__init__.py
multidocs/__main__.py
multidocs/cli.py
multidocs/config.py
multidocs/content/__init__.py
multidocs/content/markdown.py
multidocs/content/utils.py
multidocs/entities.py
multidocs/globals.py
multidocs/jinja2.py
multidocs/search.py
multidocs/settings.py
multidocs/sources/__init__.py
multidocs/sources/git.py
multidocs/sources/path.py
multidocs/templates/content.html.j2
multidocs/templates/layout.html.j2
multidocs/templates/search.html.j2
multidocs/templates/sidebar.html.j2
multidocs/web/app.py
multidocs/web/auth/__init__.py
multidocs/web/auth/github.py
multidocs/web/search.py
multidocs/web/static/button-closed.png
multidocs/web/static/button-open.png
multidocs/web/static/button.png
multidocs/web/static/collapsible-lists.js
multidocs/web/static/list-item-contents.png
multidocs/web/static/list-item-last-open.png
multidocs/web/static/list-item-last.png
multidocs/web/static/list-item-open.png
multidocs/web/static/list-item-root.png
multidocs/web/static/list-item.png
multidocs/web/static/style.css
multidocs/web/static.py
multidocs-0.1.1.dist-info/entry_points.txt
multidocs-0.1.1.dist-info/WHEEL
multidocs-0.1.1.dist-info/METADATA
multidocs-0.1.1.dist-info/RECORD
