Metadata-Version: 2.1
Name: multidocs
Version: 0.1.1
Summary: Generate documentation from multiple sources.
Home-page: UNKNOWN
License: UNKOWN
Author: Andreas Lutro
Author-email: anlutro@gmail.com
Requires-Python: >=3.6,<4.0
Classifier: Programming Language :: Python :: 3
Classifier: Programming Language :: Python :: 3.6
Classifier: Programming Language :: Python :: 3.7
Requires-Dist: bleach (>=2.1,<3.0)
Requires-Dist: commonmarkextensions (>=0.0.4,<0.0.5)
Requires-Dist: flask (>=1.0,<2.0)
Requires-Dist: flask-oauthlib (>=0.9.5,<0.10.0)
Requires-Dist: jinja2 (>=2.10,<3.0)
Requires-Dist: python-slugify (>=1.2,<2.0)
Requires-Dist: pyyaml (>=3.13,<4.0)
Requires-Dist: whoosh (>=2.7,<3.0)
